aiozoom/__init__.py
aiozoom/components/__init__.py
aiozoom/components/base.py
aiozoom/components/dashboard.py
aiozoom/components/meeting.py
aiozoom/components/recording.py
aiozoom/components/zoom.py
aiozoom/config/__init__.py
aiozoom/config/auth.py
aiozoom/config/client.py
aiozoom-0.0.9.dist-info/LICENSE
aiozoom-0.0.9.dist-info/METADATA
aiozoom-0.0.9.dist-info/WHEEL
aiozoom-0.0.9.dist-info/top_level.txt
aiozoom-0.0.9.dist-info/RECORD
