Metadata-Version: 2.1
Name: aiozoom
Version: 0.0.9
Summary: Async library for interaction with Zoom API
Home-page: https://github.com/vladisa88/aiozoom
Author: Vladislav Isakov
Author-email: vladisa88@gmail.com
License: UNKNOWN
Keywords: python,zoom,async
Platform: UNKNOWN
Classifier: Development Status :: 3 - Alpha
Classifier: Intended Audience :: Education
Classifier: Programming Language :: Python
Classifier: Programming Language :: Python :: 3
Classifier: Programming Language :: Python :: 3.8
Classifier: Programming Language :: Python :: 3.9
Classifier: Operating System :: OS Independent
Classifier: Topic :: Internet
Classifier: Topic :: Office/Business
Classifier: Topic :: Software Development :: Libraries
Requires-Dist: aiohttp
